badger_config_handler/__init__.py
badger_config_handler/badger_config_handler.py
Badger_Config_Handler_publishing_test-0.2.1.dist-info/LICENSE
Badger_Config_Handler_publishing_test-0.2.1.dist-info/METADATA
Badger_Config_Handler_publishing_test-0.2.1.dist-info/WHEEL
Badger_Config_Handler_publishing_test-0.2.1.dist-info/top_level.txt
Badger_Config_Handler_publishing_test-0.2.1.dist-info/RECORD
