Metadata-Version: 2.1
Name: Badger-Config-Handler-publishing-test
Version: 0.2.1
Summary: Config handler for code-declared and file-defined settings.
Author: pidi3000
Project-URL: Repository, https://github.com/pidi3000/Badger_Config_Handler
Keywords: settings handler,config handler,json,yaml
Classifier: Programming Language :: Python :: 3.11
Classifier: Programming Language :: Python :: 3.10
Classifier: Programming Language :: Python :: 3.9
Classifier: Programming Language :: Python :: 3.8
Classifier: Programming Language :: Python :: 3.7
Classifier: Programming Language :: Python :: 3
Classifier: Topic :: Software Development :: Libraries :: Python Modules
Classifier: License :: OSI Approved :: MIT License
Classifier: Operating System :: OS Independent
Classifier: Development Status :: 3 - Alpha
Classifier: Intended Audience :: Developers
Requires-Python: >=3.10
License-File: LICENSE
Provides-Extra: dev
Requires-Dist: build ; extra == 'dev'
Requires-Dist: twine ; extra == 'dev'
Requires-Dist: pytest ; extra == 'dev'
Requires-Dist: pytest-dependency ; extra == 'dev'
Provides-Extra: yaml
Requires-Dist: pyyaml ; extra == 'yaml'
